metasim/__init__.py
metasim/fret/__init__.py
metasim/fret/core/__init__.py
metasim/fret/core/atlas.py
metasim/fret/core/atlas_pp_density_models.joblib
metasim/fret/core/atlas_pp_distilled.h5
metasim/fret/core/data.py
metasim/fret/core/encoder-20240111-045226.h5
metasim/fret/core/linalg.py
metasim/fret/core/model.py
metasim/fret/core/score.py
metasim/fret/core/legacy/__init__.py
metasim/fret/core/legacy/dataset.py
metasim/fret/core/legacy/embedding_projector.py
metasim/fret/core/legacy/evaluation.py
metasim/fret/core/legacy/finetuning.py
metasim/fret/core/legacy/fit.py
metasim/fret/core/legacy/learning_task.py
metasim/fret/core/legacy/multi_task_learning.py
metasim/fret/core/legacy/tf_layers.py
metasim/fret/core/legacy/tf_learning.py
metasim/fret/core/legacy/trace_simulator.py
metasim/fret/core/legacy/trace_statistics.py
metasim/fret/tools/FRETSTATE.h5
metasim/fret/tools/__init__.py
metasim/fret/tools/idealize.py
metasim/fret/tools/tuning.py
metasim/fret/tools/viz.py
metasim/fret/tools/downstream_task_model_configs/ACCEPTORLIFETIME.json
metasim/fret/tools/downstream_task_model_configs/BACKGROUND.json
metasim/fret/tools/downstream_task_model_configs/COINCIDENCE.json
metasim/fret/tools/downstream_task_model_configs/DONORLIFETIME.json
metasim/fret/tools/downstream_task_model_configs/DWELLTIME.json
metasim/fret/tools/downstream_task_model_configs/FRETSTATECOUNT.json
metasim/fret/tools/downstream_task_model_configs/FRETSTATEHIGHEST.json
metasim/fret/tools/downstream_task_model_configs/FRETSTATELOWEST.json
metasim/fret/tools/downstream_task_model_configs/MULTISTEP.json
metasim/fret/tools/downstream_task_model_configs/NBD.json
metasim/fret/tools/downstream_task_model_configs/NBDQUICK.json
metasim/fret/tools/downstream_task_model_configs/NOISELEVEL.json
metasim/fret/tools/downstream_task_model_configs/SINGLECHANNELDWELLTIME.json
metasim/fret/tools/downstream_task_model_configs/SINGLECHANNELLIFETIME.json
metasim-1.0.1.dist-info/LICENSE
metasim-1.0.1.dist-info/METADATA
metasim-1.0.1.dist-info/WHEEL
metasim-1.0.1.dist-info/top_level.txt
metasim-1.0.1.dist-info/RECORD
