Metadata-Version: 2.2
Name: metasim
Version: 1.0.1
Summary: A foundation model for single-molecule time traces
Author-email: "Jieming Li, Leyou Zhang" <jmli@umich.edu>
License: MIT License
Project-URL: Homepage, https://github.com/simol-lab/META-SiM
Project-URL: Bug Tracker, https://github.com/simol-lab/META-SiM/issues
Classifier: Programming Language :: Python :: 3
Classifier: License :: OSI Approved :: MIT License
Classifier: Operating System :: OS Independent
Classifier: Topic :: Scientific/Engineering :: Bio-Informatics
Classifier: Topic :: Scientific/Engineering :: Physics
Classifier: Intended Audience :: Science/Research
License-File: LICENSE
Requires-Dist: openfret
Requires-Dist: keras<=2.15.0,>=2.13.0
Requires-Dist: tensorflow<=2.15.0,>=2.13.0
Requires-Dist: umap-learn>=0.5.3
Requires-Dist: numpy
Requires-Dist: scikit-learn>=1.0.2
Requires-Dist: matplotlib
Requires-Dist: sciplotlib>=0.0.6
Requires-Dist: joblib
